datajson/__init__.py
datajson/datajson.py
datajson-0.0.7.dist-info/LICENSE
datajson-0.0.7.dist-info/METADATA
datajson-0.0.7.dist-info/WHEEL
datajson-0.0.7.dist-info/top_level.txt
datajson-0.0.7.dist-info/RECORD
